field_history/__init__.py
field_history/admin.py
field_history/json_nested_serializer.py
field_history/managers.py
field_history/middleware.py
field_history/models.py
field_history/tracker.py
field_history/management/__init__.py
field_history/management/commands/__init__.py
field_history/management/commands/createinitialfieldhistory.py
field_history/management/commands/renamefieldhistory.py
field_history/migrations/0001_initial.py
field_history/migrations/0002_auto_20160413_1824.py
field_history/migrations/__init__.py
django_field_history-0.8.0.dist-info/AUTHORS.rst
django_field_history-0.8.0.dist-info/LICENSE
django_field_history-0.8.0.dist-info/METADATA
django_field_history-0.8.0.dist-info/WHEEL
django_field_history-0.8.0.dist-info/top_level.txt
django_field_history-0.8.0.dist-info/RECORD
